yta_math_graphic/__init__.py
yta_math_graphic/curve/__init__.py
yta_math_graphic/curve/definition.py
yta_math_graphic/curve/evaluator.py
yta_math_graphic/curve/node.py
yta_math_graphic/curve/segment/__init__.py
yta_math_graphic/curve/segment/abstract.py
yta_math_graphic/curve/segment/distribution/__init__.py
yta_math_graphic/curve/segment/distribution/abstract.py
yta_math_graphic/curve/segment/distribution/proportional.py
yta_math_graphic/curve/segment/distribution/uniform.py
yta_math_graphic/curve/segment/factory.py
yta_math_graphic/curve/segment/linear.py
yta_math_graphic/curve/segment/smootherer.py
yta_math_graphic/motion_graph/__init__.py
yta_math_graphic/motion_graph/node/__init__.py
yta_math_graphic/motion_graph/segment/__init__.py
yta_math_graphic/motion_graph/segment/abstract.py
yta_math_graphic/motion_graph/segment/factory.py
yta_math_graphic/motion_graph/segment/linear.py
yta_math_graphic/motion_graph/segment/rush_from.py
yta_math_graphic/motion_graph/segment/rush_into.py
yta_math_graphic/motion_graph/segment/smooth.py
yta_math_graphic/motion_graph/segment/smooth_step.py
yta_math_graphic/motion_graph/segment/smoother_step.py
yta_math_graphic/motion_graph/segment/smootherer_step.py
yta_math_graphic-0.0.8.dist-info/licenses/LICENSE
yta_math_graphic-0.0.8.dist-info/METADATA
yta_math_graphic-0.0.8.dist-info/WHEEL
yta_math_graphic-0.0.8.dist-info/RECORD
