Metadata-Version: 2.4
Name: yta-math-graphic
Version: 0.0.8
Summary: Youtube Autonomous Math Graphic Module.
License-File: LICENSE
Author: danialcala94
Author-email: danielalcalavalera@gmail.com
Requires-Python: ==3.9
Classifier: Programming Language :: Python :: 3
Classifier: Programming Language :: Python :: 3.9
Requires-Dist: numpy (>=1.22.0,<3.0.0)
Requires-Dist: yta_math_easings (>=0.0.1,<1.0.0)
Requires-Dist: yta_math_interpolation (>=0.0.1,<1.0.0)
Requires-Dist: yta_programming (>=0.0.1,<1.0.0)
Requires-Dist: yta_validation (>=0.0.1,<1.0.0)
